2024122002_Project/2024122002_Project/VERILOG/verilog_implement.v
module CLA_with_DFF (
    input [3:0] A, B,         // 4-bit inputs
    input Cin,                // Carry-in
    input Clk,                // Clock signal
    input Reset,              // Reset signal
    output [3:0] Sum_out,     // 4-bit sum output (stored in D flip-flops)
    output Cout_out           // Carry-out (stored in a D flip-flop)
);
    wire [3:0] G, P;          // Generate and Propagate wires
    wire [3:0] C;             // Internal carry wires
    wire [3:0] Sum;           // Sum calculation wires
    wire Cout;                // Final carry-out
    wire [3:0] Sum_reg;       // Registered sum output
    wire Cout_reg;            // Registered carry-out output

    // Generate and Propagate Logic
    assign G = A & B;         // Generate: G[i] = A[i] & B[i]
    assign P = A ^ B;         // Propagate: P[i] = A[i] ^ B[i]

    // Carry Lookahead Logic
    assign C[0] = Cin;                           // First carry bit = Cin
    assign C[1] = G[0] | (P[0] & C[0]);          // C[1] = G[0] + P[0] * C[0]
    assign C[2] = G[1] | (P[1] & G[0]) | (P[1] & P[0] & C[0]);
    assign C[3] = G[2] | (P[2] & G[1]) | (P[2] & P[1] & G[0]) | (P[2] & P[1] & P[0] & C[0]);
    assign Cout = G[3] | (P[3] & G[2]) | (P[3] & P[2] & G[1]) | (P[3] & P[2] & P[1] & G[0]) | (P[3] & P[2] & P[1] & P[0] & C[0]);

    // Sum Calculation
    assign Sum = P ^ C;       // Sum[i] = P[i] ^ C[i]

    // D Flip-Flops for Registered Outputs
    DFlipFlop DFF0 (.D(Sum[0]), .Clk(Clk), .Reset(Reset), .Q(Sum_reg[0]));
    DFlipFlop DFF1 (.D(Sum[1]), .Clk(Clk), .Reset(Reset), .Q(Sum_reg[1]));
    DFlipFlop DFF2 (.D(Sum[2]), .Clk(Clk), .Reset(Reset), .Q(Sum_reg[2]));
    DFlipFlop DFF3 (.D(Sum[3]), .Clk(Clk), .Reset(Reset), .Q(Sum_reg[3]));
    DFlipFlop DFFC (.D(Cout),  .Clk(Clk), .Reset(Reset), .Q(Cout_reg));

    // Assign Registered Outputs
    assign Sum_out = Sum_reg;
    assign Cout_out = Cout_reg;
endmodule

// D Flip-Flop Module
module DFlipFlop (
    input D,         // Data input
    input Clk,       // Clock input
    input Reset,     // Synchronous Reset input
    output reg Q     // Data output
);
    always @(posedge Clk) begin
        if (Reset)
            Q <= 0;   // Reset Q to 0
        else
            Q <= D;   // Store D in Q on clock edge
    end
endmodule

2024122002_Project/2024122002_Project/VERILOG/CLA_testbench.v
`timescale 1ns / 1ps
`include "verilog_implement.v"
module CLA_with_DFF_tb;

    // Testbench signals
    reg [3:0] A_tb, B_tb;      // 4-bit inputs
    reg Cin_tb;                // Carry-in
    reg Clk_tb;                // Clock signal
    reg Reset_tb;              // Reset signal
    wire [3:0] Sum_out_tb;     // 4-bit sum output
    wire Cout_out_tb;          // Carry-out output

    // Instantiate the CLA_with_DFF module
    CLA_with_DFF uut (
        .A(A_tb),
        .B(B_tb),
        .Cin(Cin_tb),
        .Clk(Clk_tb),
        .Reset(Reset_tb),
        .Sum_out(Sum_out_tb),
        .Cout_out(Cout_out_tb)
    );

    // Clock generation (50% duty cycle, period = 10ns)
    initial begin
        Clk_tb = 0;
        forever #5 Clk_tb = ~Clk_tb; // Toggle clock every 5ns
    end

    // Test sequence
    initial begin
        // Initialize inputs
        $dumpfile("tb.vcd");
        $dumpvars(0,CLA_with_DFF_tb);
        A_tb = 4'b0000;
        B_tb = 4'b0000;
        Cin_tb = 0;
        Reset_tb = 1;

        // Apply Reset
        #10 Reset_tb = 0; A_tb=4'b1001; B_tb=1101; // Deactivate reset after 10ns
        #10 A_tb=4'b0101; B_tb=4'b1010;
        #10 A_tb=4'b1101; B_tb=4'b1011;
        #20;
        $finish;
    end

    // Monitor outputs
    initial begin
        $monitor($time, " A = %b, B = %b, Cin = %b, Sum = %b, Cout = %b",
                 A_tb, B_tb, Cin_tb, Sum_out_tb, Cout_out_tb);
    end

endmodule

2024122002_Project/2024122002_Project/VERILOG/tb.vcd
$date
	Tue Dec 03 07:04:32 2024
$end
$version
	Icarus Verilog
$end
$timescale
	1ps
$end
$scope module CLA_with_DFF_tb $end
$var wire 4 ! Sum_out_tb [3:0] $end
$var wire 1 " Cout_out_tb $end
$var reg 4 # A_tb [3:0] $end
$var reg 4 $ B_tb [3:0] $end
$var reg 1 % Cin_tb $end
$var reg 1 & Clk_tb $end
$var reg 1 ' Reset_tb $end
$scope module uut $end
$var wire 4 ( A [3:0] $end
$var wire 4 ) B [3:0] $end
$var wire 1 % Cin $end
$var wire 1 & Clk $end
$var wire 1 * Cout $end
$var wire 1 " Cout_out $end
$var wire 4 + G [3:0] $end
$var wire 4 , P [3:0] $end
$var wire 1 ' Reset $end
$var wire 4 - Sum [3:0] $end
$var wire 4 . Sum_out [3:0] $end
$var wire 4 / Sum_reg [3:0] $end
$var wire 1 0 Cout_reg $end
$var wire 4 1 C [3:0] $end
$scope module DFF0 $end
$var wire 1 & Clk $end
$var wire 1 2 D $end
$var wire 1 ' Reset $end
$var reg 1 3 Q $end
$upscope $end
$scope module DFF1 $end
$var wire 1 & Clk $end
$var wire 1 4 D $end
$var wire 1 ' Reset $end
$var reg 1 5 Q $end
$upscope $end
$scope module DFF2 $end
$var wire 1 & Clk $end
$var wire 1 6 D $end
$var wire 1 ' Reset $end
$var reg 1 7 Q $end
$upscope $end
$scope module DFF3 $end
$var wire 1 & Clk $end
$var wire 1 8 D $end
$var wire 1 ' Reset $end
$var reg 1 9 Q $end
$upscope $end
$scope module DFFC $end
$var wire 1 & Clk $end
$var wire 1 * D $end
$var wire 1 ' Reset $end
$var reg 1 0 Q $end
$upscope $end
$upscope $end
$upscope $end
$enddefinitions $end
#0
$dumpvars
x9
08
x7
06
x5
04
x3
02
b0 1
x0
bx /
bx .
b0 -
b0 ,
b0 +
0*
b0 )
b0 (
1'
0&
0%
b0 $
b0 #
x"
bx !
$end
#5000
03
05
07
b0 !
b0 .
b0 /
09
0"
00
1&
#10000
1*
14
b10 1
16
b110 -
b1001 +
b100 ,
0&
b1101 $
b1101 )
b1001 #
b1001 (
0'
#15000
1"
10
17
b110 !
b110 .
b110 /
15
1&
#20000
0*
b0 1
12
14
18
b1111 -
b0 +
b1111 ,
0&
b1010 $
b1010 )
b101 #
b101 (
#25000
13
b1111 !
b1111 .
b1111 /
19
0"
00
1&
#30000
06
04
1*
b1110 1
02
18
b1000 -
b1001 +
b110 ,
0&
b1011 $
b1011 )
b1101 #
b1101 (
#35000
1"
10
07
05
b1000 !
b1000 .
b1000 /
03
1&
